pymcssa/__init__.py
pymcssa/core.py
pymcssa/mcssa.py
pymcssa/ssa.py
pymcssa/utils.py
pymcssa-0.1.1.dist-info/licenses/LICENSE
pymcssa-0.1.1.dist-info/METADATA
pymcssa-0.1.1.dist-info/WHEEL
pymcssa-0.1.1.dist-info/top_level.txt
pymcssa-0.1.1.dist-info/RECORD
