Metadata-Version: 2.4
Name: pymcssa
Version: 0.1.1
Summary: A Monte Carlo Singular Spectrum Analysis (MCSSA) package for time series analysis.
Home-page: https://github.com/sayan-geoDL/pymcssa
Author: Sayan Jana
Author-email: Sayan Jana <janasayan143@gmail.com>
License: MIT License
Project-URL: Homepage, https://github.com/sayan-geoDL/pymcssa
Project-URL: Repository, https://github.com/sayan-geoDL/pymcssa
Project-URL: Documentation, https://sayan-geoDL.github.io/pymcssa/
Project-URL: Issues, https://github.com/sayan-geoDL/pymcssa/issues
Keywords: time-series,signal-processing,mcssa,ssa,statistics,spectral-analysis
Classifier: Programming Language :: Python :: 3
Classifier: License :: OSI Approved :: MIT License
Classifier: Operating System :: OS Independent
Classifier: Topic :: Scientific/Engineering :: Information Analysis
Classifier: Intended Audience :: Science/Research
Requires-Python: >=3.8
License-File: LICENSE
Requires-Dist: numpy<2.0,>=1.26
Dynamic: author
Dynamic: home-page
Dynamic: license-file
Dynamic: requires-python
